{
  "name": "StudentPastData",
  "options": {
    "idInjection": false,
    "mssql": {
      "schema": "dbo",
      "table": "STUDENT_PAST_DATA"
    },
    "relations": {}
  },
  "properties": {
    "sId": {
      "type": "Number",
      "required": false,
      "id":1,
      "length": null,
      "precision": 10,
      "scale": 0,
      "mssql": {
        "columnName": "S_ID",
        "dataType": "int",
        "dataLength": null,
        "dataPrecision": 10,
        "dataScale": 0,
        "nullable": "YES"
      }
    },
    "cId": {
      "type": "String",
      "required": false,
      "length": 255,
      "id":2,
      "precision": null,
      "scale": null,
      "mssql": {
        "columnName": "C_ID",
        "dataType": "nvarchar",
        "dataLength": 255,
        "dataPrecision": null,
        "dataScale": null,
        "nullable": "YES"
      }
    },
    "cName": {
      "type": "String",
      "required": false,
      "length": 255,
      "precision": null,
      "scale": null,
      "mssql": {
        "columnName": "C_NAME",
        "dataType": "nvarchar",
        "dataLength": 255,
        "dataPrecision": null,
        "dataScale": null,
        "nullable": "YES"
      }
    },
    "cSemester": {
      "type": "String",
      "required": false,
      "length": 255,
      "precision": null,
      "scale": null,
      "mssql": {
        "columnName": "C_SEMESTER",
        "dataType": "nvarchar",
        "dataLength": 255,
        "dataPrecision": null,
        "dataScale": null,
        "nullable": "YES"
      }
    },
    "cGrade": {
      "type": "String",
      "required": false,
      "length": 255,
      "precision": null,
      "scale": null,
      "mssql": {
        "columnName": "C_GRADE",
        "dataType": "nvarchar",
        "dataLength": 255,
        "dataPrecision": null,
        "dataScale": null,
        "nullable": "YES"
      }
    },
    "cStatus": {
      "type": "String",
      "required": false,
      "length": 255,
      "precision": null,
      "scale": null,
      "mssql": {
        "columnName": "C_STATUS",
        "dataType": "nvarchar",
        "dataLength": 255,
        "dataPrecision": null,
        "dataScale": null,
        "nullable": "YES"
      }
    }
  }
}
